[
  {
    "type": "event",
    "name": "SetSpokeImmutables",
    "inputs": [
      { "indexed": true, "name": "oracle", "type": "address" },
      { "indexed": false, "name": "maxUserReservesLimit", "type": "uint16" }
    ],
    "anonymous": false
  },
  {
    "type": "event",
    "name": "UpdateLiquidationConfig",
    "inputs": [
      {
        "indexed": false,
        "name": "config",
        "type": "tuple",
        "components": [
          { "name": "targetHealthFactor", "type": "uint128" },
          { "name": "healthFactorForMaxBonus", "type": "uint64" },
          { "name": "liquidationBonusFactor", "type": "uint16" }
        ]
      }
    ],
    "anonymous": false
  },
  {
    "type": "event",
    "name": "AddReserve",
    "inputs": [
      { "indexed": true, "name": "reserveId", "type": "uint256" },
      { "indexed": true, "name": "assetId", "type": "uint256" },
      { "indexed": true, "name": "hub", "type": "address" }
    ],
    "anonymous": false
  },
  {
    "type": "event",
    "name": "UpdateReserveConfig",
    "inputs": [
      { "indexed": true, "name": "reserveId", "type": "uint256" },
      {
        "indexed": false,
        "name": "config",
        "type": "tuple",
        "components": [
          { "name": "collateralRisk", "type": "uint24" },
          { "name": "paused", "type": "bool" },
          { "name": "frozen", "type": "bool" },
          { "name": "borrowable", "type": "bool" },
          { "name": "receiveSharesEnabled", "type": "bool" }
        ]
      }
    ],
    "anonymous": false
  },
  {
    "type": "event",
    "name": "UpdateReservePriceSource",
    "inputs": [
      { "indexed": true, "name": "reserveId", "type": "uint256" },
      { "indexed": true, "name": "priceSource", "type": "address" }
    ],
    "anonymous": false
  },
  {
    "type": "event",
    "name": "AddDynamicReserveConfig",
    "inputs": [
      { "indexed": true, "name": "reserveId", "type": "uint256" },
      { "indexed": true, "name": "dynamicConfigKey", "type": "uint32" },
      {
        "indexed": false,
        "name": "config",
        "type": "tuple",
        "components": [
          { "name": "collateralFactor", "type": "uint16" },
          { "name": "maxLiquidationBonus", "type": "uint32" },
          { "name": "liquidationFee", "type": "uint16" }
        ]
      }
    ],
    "anonymous": false
  },
  {
    "type": "event",
    "name": "UpdateDynamicReserveConfig",
    "inputs": [
      { "indexed": true, "name": "reserveId", "type": "uint256" },
      { "indexed": true, "name": "dynamicConfigKey", "type": "uint32" },
      {
        "indexed": false,
        "name": "config",
        "type": "tuple",
        "components": [
          { "name": "collateralFactor", "type": "uint16" },
          { "name": "maxLiquidationBonus", "type": "uint32" },
          { "name": "liquidationFee", "type": "uint16" }
        ]
      }
    ],
    "anonymous": false
  },
  {
    "type": "event",
    "name": "UpdatePositionManager",
    "inputs": [
      { "indexed": true, "name": "positionManager", "type": "address" },
      { "indexed": false, "name": "active", "type": "bool" }
    ],
    "anonymous": false
  },
  {
    "type": "event",
    "name": "Supply",
    "inputs": [
      { "indexed": true, "name": "reserveId", "type": "uint256" },
      { "indexed": true, "name": "caller", "type": "address" },
      { "indexed": true, "name": "user", "type": "address" },
      { "indexed": false, "name": "suppliedShares", "type": "uint256" },
      { "indexed": false, "name": "suppliedAmount", "type": "uint256" }
    ],
    "anonymous": false
  },
  {
    "type": "event",
    "name": "Withdraw",
    "inputs": [
      { "indexed": true, "name": "reserveId", "type": "uint256" },
      { "indexed": true, "name": "caller", "type": "address" },
      { "indexed": true, "name": "user", "type": "address" },
      { "indexed": false, "name": "withdrawnShares", "type": "uint256" },
      { "indexed": false, "name": "withdrawnAmount", "type": "uint256" }
    ],
    "anonymous": false
  },
  {
    "type": "event",
    "name": "Borrow",
    "inputs": [
      { "indexed": true, "name": "reserveId", "type": "uint256" },
      { "indexed": true, "name": "caller", "type": "address" },
      { "indexed": true, "name": "user", "type": "address" },
      { "indexed": false, "name": "drawnShares", "type": "uint256" },
      { "indexed": false, "name": "drawnAmount", "type": "uint256" }
    ],
    "anonymous": false
  },
  {
    "type": "event",
    "name": "Repay",
    "inputs": [
      { "indexed": true, "name": "reserveId", "type": "uint256" },
      { "indexed": true, "name": "caller", "type": "address" },
      { "indexed": true, "name": "user", "type": "address" },
      { "indexed": false, "name": "drawnShares", "type": "uint256" },
      { "indexed": false, "name": "totalAmountRepaid", "type": "uint256" },
      {
        "indexed": false,
        "name": "premiumDelta",
        "type": "tuple",
        "components": [
          { "name": "sharesDelta", "type": "int256" },
          { "name": "offsetRayDelta", "type": "int256" },
          { "name": "restoredPremiumRay", "type": "uint256" }
        ]
      }
    ],
    "anonymous": false
  },
  {
    "type": "event",
    "name": "LiquidationCall",
    "inputs": [
      { "indexed": true, "name": "collateralReserveId", "type": "uint256" },
      { "indexed": true, "name": "debtReserveId", "type": "uint256" },
      { "indexed": true, "name": "user", "type": "address" },
      { "indexed": false, "name": "liquidator", "type": "address" },
      { "indexed": false, "name": "receiveShares", "type": "bool" },
      { "indexed": false, "name": "debtAmountRestored", "type": "uint256" },
      { "indexed": false, "name": "drawnSharesLiquidated", "type": "uint256" },
      {
        "indexed": false,
        "name": "premiumDelta",
        "type": "tuple",
        "components": [
          { "name": "sharesDelta", "type": "int256" },
          { "name": "offsetRayDelta", "type": "int256" },
          { "name": "restoredPremiumRay", "type": "uint256" }
        ]
      },
      { "indexed": false, "name": "collateralAmountRemoved", "type": "uint256" },
      { "indexed": false, "name": "collateralSharesLiquidated", "type": "uint256" },
      { "indexed": false, "name": "collateralSharesToLiquidator", "type": "uint256" }
    ],
    "anonymous": false
  },
  {
    "type": "event",
    "name": "ReportDeficit",
    "inputs": [
      { "indexed": true, "name": "reserveId", "type": "uint256" },
      { "indexed": true, "name": "user", "type": "address" },
      { "indexed": false, "name": "drawnShares", "type": "uint256" },
      {
        "indexed": false,
        "name": "premiumDelta",
        "type": "tuple",
        "components": [
          { "name": "sharesDelta", "type": "int256" },
          { "name": "offsetRayDelta", "type": "int256" },
          { "name": "restoredPremiumRay", "type": "uint256" }
        ]
      }
    ],
    "anonymous": false
  },
  {
    "type": "event",
    "name": "SetUsingAsCollateral",
    "inputs": [
      { "indexed": true, "name": "reserveId", "type": "uint256" },
      { "indexed": true, "name": "caller", "type": "address" },
      { "indexed": true, "name": "user", "type": "address" },
      { "indexed": false, "name": "usingAsCollateral", "type": "bool" }
    ],
    "anonymous": false
  },
  {
    "type": "event",
    "name": "UpdateUserRiskPremium",
    "inputs": [
      { "indexed": true, "name": "user", "type": "address" },
      { "indexed": false, "name": "riskPremium", "type": "uint256" }
    ],
    "anonymous": false
  },
  {
    "type": "event",
    "name": "RefreshAllUserDynamicConfig",
    "inputs": [
      { "indexed": true, "name": "user", "type": "address" }
    ],
    "anonymous": false
  },
  {
    "type": "event",
    "name": "RefreshSingleUserDynamicConfig",
    "inputs": [
      { "indexed": true, "name": "user", "type": "address" },
      { "indexed": false, "name": "reserveId", "type": "uint256" }
    ],
    "anonymous": false
  },
  {
    "type": "event",
    "name": "SetUserPositionManager",
    "inputs": [
      { "indexed": true, "name": "user", "type": "address" },
      { "indexed": true, "name": "positionManager", "type": "address" },
      { "indexed": false, "name": "approve", "type": "bool" }
    ],
    "anonymous": false
  },
  {
    "type": "event",
    "name": "RefreshPremiumDebt",
    "inputs": [
      { "indexed": true, "name": "reserveId", "type": "uint256" },
      { "indexed": true, "name": "user", "type": "address" },
      {
        "indexed": false,
        "name": "premiumDelta",
        "type": "tuple",
        "components": [
          { "name": "sharesDelta", "type": "int256" },
          { "name": "offsetRayDelta", "type": "int256" },
          { "name": "restoredPremiumRay", "type": "uint256" }
        ]
      }
    ],
    "anonymous": false
  }
]
